{
   "historyList":[
    {
      "name": "projectTest",
      "projPath": "E:/demo",
      "creationTime": "2024-04-01 13:11:21",
      "lastSavaTime": "2024-04-01 14:11:21"
    },
    {
      "name": "projectTest_1",
      "projPath": "E:/demo",
      "creationTime": "2024-04-02 13:11:21",
      "lastSavaTime": "2024-04-02 14:11:21"
    },
    {
      "name": "projectTest_2",
      "projPath": "E:/demo",
      "creationTime": "2024-04-03 13:11:21",
      "lastSavaTime": "2024-04-03 14:11:21"
    },
    {
      "name": "projectTest_3",
      "projPath": "E:/demo",
      "creationTime": "2024-04-04 13:11:21",
      "lastSavaTime": "2024-04-04 14:11:21"
    }
  ]
}